{
  "id": "template-083",
  "slug": "woodwork-studio",
  "name": "Woodwork Studio",
  "description": "Woodwork Studio - 專為空間生活產業設計的全功能網站樣板。採用Storytelling 長卷軸版型設計，打造專業的品牌形象網站。",
  "industry": "空間生活",
  "industryCategory": "空間",
  "colorTheme": "#3a2a1a, #5a3a1a, #8a5a2a, #b88a4a, #e0d0b8",
  "layoutType": "Storytelling 長卷軸",
  "previewImage": "assets/img/preview.jpg",
  "zipFile": "../../downloads/template-083-woodwork-studio.zip",
  "hasZip": false,
  "promptFile": "prompt.md",
  "pageCount": 12,
  "imageRich": true,
  "imagePolicy": "圖片僅作為設計示意。",
  "pages": ["index.html","about.html","services.html","service-detail.html","portfolio.html","reviews.html","faq.html","booking.html","process.html","blog.html","blog-detail.html","contact.html"]
}
